pewdie.py
pewdiepy-0.0.1.dist-info/METADATA
pewdiepy-0.0.1.dist-info/WHEEL
pewdiepy-0.0.1.dist-info/licenses/LICENCE
pewdiepy-0.0.1.dist-info/RECORD
