Metadata-Version: 2.1
Name: pewdiepy
Version: 0.0.1
Summary: A python package to claim the name pewdiepy on pypa. No utility yet.
Project-URL: Homepage, https://github.com/sharshub/pewdiepy
Project-URL: Bug Tracker, https://github.com/sharshub/pewdiepy/issues
Author-email: Shubham Sharma <sharshub@users.noreply.github.com>
License-File: LICENCE
Classifier: License :: OSI Approved :: MIT License
Classifier: Operating System :: OS Independent
Classifier: Programming Language :: Python :: 3
Requires-Python: >=3.7
